Project/project/CA_project/task_C/rtl/switches.v
`timescale 1ns / 1ps
//////////////////////////////////////////////////////////////////////////////////
// Company: 
// Engineer: 
// 
// Create Date: 04/28/2026 03:30:55 PM
// Design Name: 
// Module Name: switches
// Project Name: 
// Target Devices: 
// Tool Versions: 
// Description: 
// 
// Dependencies: 
// 
// Revision:
// Revision 0.01 - File Created
// Additional Comments:
// 
//////////////////////////////////////////////////////////////////////////////////

`timescale 1ns / 1ps
module switches(
    input clk,
    input rst,
    input [15:0] btns,
    input [15:0] switches,
    input readEnable,
    input [31:0] writeData,
    input writeEnable,
    output reg [31:0] readData
);

    always @(posedge clk) begin
        if (rst)
            readData <= 32'b0;
        else
            readData <= {16'b0, switches};
    end

endmodule

Project/project/CA_project/task_C/rtl/leds.v
`timescale 1ns / 1ps
//////////////////////////////////////////////////////////////////////////////////
// Company: 
// Engineer: 
// 
// Create Date: 04/28/2026 03:28:25 PM
// Design Name: 
// Module Name: leds
// Project Name: 
// Target Devices: 
// Tool Versions: 
// Description: 
// 
// Dependencies: 
// 
// Revision:
// Revision 0.01 - File Created
// Additional Comments:
// 
//////////////////////////////////////////////////////////////////////////////////
module leds(
    input clk,
    input rst,
    input [15:0] btns,
    input [31:0] writeData,
    input writeEnable,
    input readEnable,
    input [29:0] memAddress,
    input [15:0] switches,
    output reg [31:0] readData
);
    always @(posedge clk or posedge rst) begin
        if (rst)
            readData <= 32'b0;
        else if (writeEnable)
            readData <= writeData;
    end
endmodule

Lab 07/project_1/project_1.srcs/sources_1/new/data_memory_mod.v
`timescale 1ns / 1ps
//////////////////////////////////////////////////////////////////////////////////
// Company: 
// Engineer: 
// 
// Create Date: 03/12/2026 09:36:51 AM
// Design Name: 
// Module Name: data_memory_mod
// Project Name: 
// Target Devices: 
// Tool Versions: 
// Description: 
// 
// Dependencies: 
// 
// Revision:
// Revision 0.01 - File Created
// Additional Comments:
// 
//////////////////////////////////////////////////////////////////////////////////


module data_memory_mod(
    input clk, memWrite,
    input [9:0] address,
    input [31:0] writeData,
    output [31:0] readData
    );
    
    reg [31:0] memory [0:511];
    
    always @(posedge clk) begin
        if (memWrite) memory[address[7:0]]<=writeData;
    end
    
    assign readData=memory[address[7:0]];
    
    
endmodule

Lab 07/project_1/project_1.srcs/sources_1/new/address_decoder.v
`timescale 1ns / 1ps
//////////////////////////////////////////////////////////////////////////////////
// Company: 
// Engineer: 
// 
// Create Date: 03/12/2026 09:46:07 AM
// Design Name: 
// Module Name: address_decoder
// Project Name: 
// Target Devices: 
// Tool Versions: 
// Description: 
// 
// Dependencies: 
// 
// Revision:
// Revision 0.01 - File Created
// Additional Comments:
// 
//////////////////////////////////////////////////////////////////////////////////


module address_decoder(
    input[9:0] address,
    output reg dataMemRead, dataMemWrite, LEDWrite, SwitchReadEnable
    );
    
    always @ (*) begin
    dataMemRead=0;
    dataMemWrite=0;
    LEDWrite=0;
    SwitchReadEnable=0; 
        if (address[9:8]==2'b00) begin dataMemRead=1; dataMemWrite=1; end
        else if(address[9:8]==2'b01)LEDWrite=1;
        else if (address[9:8] == 2'b10) SwitchReadEnable = 1;   
    end 
endmodule

Lab 07/project_1/project_1.srcs/sources_1/new/addressDecoderTop.v
`timescale 1ns / 1ps
module addressDecoderTop(
    input         clk,
    input         rst,
    input  [31:0] address,
    input         readEnable,
    input         writeEnable,
    input  [31:0] writeData,
    input  [15:0] switches,
    output [31:0] readData,
    output [15:0] leds
);

    // ?? Address decoder ??????????????????????????????????????????????????????
    wire dec_dataMemRead, dec_dataMemWrite;
    wire dec_LEDWrite, dec_SwitchRead;

    address_decoder u_addr_dec (
        .address         (address[9:0]),
        .dataMemRead     (dec_dataMemRead),
        .dataMemWrite    (dec_dataMemWrite),
        .LEDWrite        (dec_LEDWrite),
        .SwitchReadEnable(dec_SwitchRead)
    );

    // ?? Gated enables ????????????????????????????????????????????????????????
    wire dataMem_writeEn = dec_dataMemWrite & writeEnable;
    wire led_writeEn     = dec_LEDWrite     & writeEnable;
    wire sw_readEn       = dec_SwitchRead   & readEnable;

    // ?? Per-device read data ?????????????????????????????????????????????????
    wire [31:0] dataMem_rdata;
    wire [31:0] led_rdata;
    wire [31:0] sw_rdata;

    // ?? Submodules ???????????????????????????????????????????????????????????
    data_memory_mod u_data_mem (
        .clk      (clk),
        .memWrite (dataMem_writeEn),
        .address  (address[9:0]),
        .writeData(writeData),
        .readData (dataMem_rdata)
    );

    leds u_leds (
        .clk        (clk),
        .rst        (rst),
        .btns       (16'b0),
        .writeData  (writeData),
        .writeEnable(led_writeEn),
        .readEnable (1'b0),
        .memAddress (address[31:2]),
        .switches   (switches),
        .readData   (led_rdata)
    );

    switches u_switches (
        .clk        (clk),
        .rst        (rst),
        .btns       (16'b0),
        .switches   (switches),
        .readEnable (sw_readEn),
        .writeData  (32'b0),
        .writeEnable(1'b0),
        .readData   (sw_rdata)
    );

    // ?? Read data mux ????????????????????????????????????????????????????????
    assign readData = (address[9:8] == 2'b00) ? dataMem_rdata :
                      (address[9:8] == 2'b10) ? sw_rdata      :
                                                32'b0;

    // ?? LED output ???????????????????????????????????????????????????????????
    assign leds = led_rdata[15:0];

endmodule

Lab 07/project_1/project_1.srcs/sim_1/new/addressDecoderTop_tb.v
`timescale 1ns / 1ps
module addressDecoderTop_tb;

    // ?? DUT ports ????????????????????????????????????????????????????????????
    reg         clk, rst;
    reg  [31:0] address;
    reg         readEnable, writeEnable;
    reg  [31:0] writeData;
    reg  [15:0] switches;
    wire [31:0] readData;
    wire [15:0] leds;

    // ?? Instantiate DUT ??????????????????????????????????????????????????????
    addressDecoderTop dut (
        .clk        (clk),
        .rst        (rst),
        .address    (address),
        .readEnable (readEnable),
        .writeEnable(writeEnable),
        .writeData  (writeData),
        .switches   (switches),
        .readData   (readData),
        .leds       (leds)
    );

    // ?? Clock ????????????????????????????????????????????????????????????????
    initial clk = 0;
    always #5 clk = ~clk;

    // ?? Pass/fail counters ???????????????????????????????????????????????????
    integer pass = 0, fail = 0;

    initial begin


        // ---------- Initialise ----------
        rst         = 1;
        address     = 0;
        readEnable  = 0;
        writeEnable = 0;
        writeData   = 0;
        switches    = 0;
        @(posedge clk); @(posedge clk);
        rst = 0;
        @(posedge clk); @(posedge clk);

        $display("========== TEST START ==========");

        // =====================================================================
        // TEST 1: Write to Data Memory
        // address=50  ?  address[9:8]=00  ?  dataMemWrite=1
        // decoder enables data memory only, stores 0xDEADBEEF at word 50
        // no readData to check here - write has no return value
        // =====================================================================
        $display("\n-- Test 1: Write to Data Memory --");
        @(negedge clk);
        address     = 32'd50;
        writeData   = 32'hDEADBEEF;
        writeEnable = 1;
        readEnable  = 0;
        @(posedge clk); #1;
        writeEnable = 0;
        @(posedge clk); @(posedge clk);
        $display("INFO: Wrote 0xDEADBEEF to Data Memory at address 50");
        $display("INFO: address[9:8] = 00 ? dataMemWrite asserted, LEDWrite=0, SwitchReadEnable=0");

        // =====================================================================
        // TEST 2: Read from Data Memory
        // address=50  ?  address[9:8]=00  ?  dataMemRead=1
        // readData should return 0xDEADBEEF written in Test 1
        // =====================================================================
        $display("\n-- Test 2: Read from Data Memory --");
        @(negedge clk);
        address     = 32'd50;
        readEnable  = 1;
        writeEnable = 0;
        @(posedge clk); #1;
        readEnable  = 0;
        @(posedge clk); @(posedge clk);
        #2;
        if (readData === 32'hDEADBEEF) begin
            $display("PASS: readData = 0x%08X (correct)", readData);
            pass = pass + 1;
        end else begin
            $display("FAIL: readData = 0x%08X, expected 0xDEADBEEF", readData);
            fail = fail + 1;
        end

        // =====================================================================
        // TEST 3: Read from Switches
        // switches=0xF0F0, address=512  ?  address[9:8]=10  ?  SwitchReadEnable=1
        // readData should return 0x0000F0F0
        // =====================================================================
        $display("\n-- Test 3: Read from Switches --");
        @(negedge clk);
        switches    = 16'hF0F0;
        address     = 32'd512;
        readEnable  = 1;
        writeEnable = 0;
        @(posedge clk); #1;
        readEnable  = 0;
        @(posedge clk); @(posedge clk);
        #2;
        if (readData === 32'h0000F0F0) begin
            $display("PASS: readData = 0x%08X (correct)", readData);
            pass = pass + 1;
        end else begin
            $display("FAIL: readData = 0x%08X, expected 0x0000F0F0", readData);
            fail = fail + 1;
        end

        // =====================================================================
        // TEST 4: Write to LEDs
        // address=256  ?  address[9:8]=01  ?  LEDWrite=1
        // leds output should show 0xABCD after write
        // =====================================================================
        $display("\n-- Test 4: Write to LEDs --");
        @(negedge clk);
        address     = 32'd256;
        writeData   = 32'h0000ABCD;
        writeEnable = 1;
        readEnable  = 0;
        @(posedge clk); #1;
        writeEnable = 0;
        @(posedge clk); @(posedge clk); // extra cycles for leds module to update
        #2;
        if (leds === 16'hABCD) begin
            $display("PASS: leds = 0x%04X (correct)", leds);
            pass = pass + 1;
        end else begin
            $display("FAIL: leds = 0x%04X, expected 0xABCD", leds);
            fail = fail + 1;
        end

        // ?? Summary ??????????????????????????????????????????????????????????
        @(posedge clk); @(posedge clk);
        $display("\n========== RESULTS: %0d PASSED, %0d FAILED ==========", pass, fail);
        $finish;
    end

endmodule

Lab 07/project_1/project_1.sim/sim_1/behav/xsim/addressDecoderTop_tb.vcd
$date
   Wed Mar 18 15:31:31 2026
$end
$version
  2020.1
$end
$timescale
  1ps
$end
$scope module addressDecoderTop_tb $end
$var reg 1 ! clk $end
$var reg 1 " rst $end
$var reg 32 # address [31:0] $end
$var reg 1 $ readEnable $end
$var reg 1 % writeEnable $end
$var reg 32 & writeData [31:0] $end
$var reg 16 ' switches [15:0] $end
$var wire 32 ( readData [31:0] $end
$var wire 16 ) leds [15:0] $end
$var integer 32 * pass $end
$var integer 32 + fail $end
$scope module dut $end
$var wire 1 , clk $end
$var wire 1 - rst $end
$var wire 32 . address [31:0] $end
$var wire 1 / readEnable $end
$var wire 1 0 writeEnable $end
$var wire 32 1 writeData [31:0] $end
$var wire 16 2 switches [15:0] $end
$var wire 32 ( readData [31:0] $end
$var wire 16 ) leds [15:0] $end
$var wire 1 3 dec_dataMemRead $end
$var wire 1 4 dec_dataMemWrite $end
$var wire 1 5 dec_LEDWrite $end
$var wire 1 6 dec_SwitchRead $end
$var wire 1 7 dataMem_writeEn $end
$var wire 1 8 led_writeEn $end
$var wire 1 9 sw_readEn $end
$var wire 32 : dataMem_rdata [31:0] $end
$var wire 32 ; led_rdata [31:0] $end
$var wire 32 < sw_rdata [31:0] $end
$scope module u_addr_dec $end
$var wire 10 = address [9:0] $end
$var reg 1 > dataMemRead $end
$var reg 1 ? dataMemWrite $end
$var reg 1 @ LEDWrite $end
$var reg 1 A SwitchReadEnable $end
$upscope $end
$scope module u_data_mem $end
$var wire 1 , clk $end
$var wire 1 7 memWrite $end
$var wire 10 = address [9:0] $end
$var wire 32 1 writeData [31:0] $end
$var wire 32 : readData [31:0] $end
$upscope $end
$scope module u_leds $end
$var wire 1 , clk $end
$var wire 1 - rst $end
$var wire 16 B btns [15:0] $end
$var wire 32 1 writeData [31:0] $end
$var wire 1 8 writeEnable $end
$var wire 1 C readEnable $end
$var wire 30 D memAddress [29:0] $end
$var wire 16 2 switches [15:0] $end
$var reg 32 E readData [31:0] $end
$upscope $end
$scope module u_switches $end
$var wire 1 , clk $end
$var wire 1 - rst $end
$var wire 16 F btns [15:0] $end
$var wire 16 2 switches [15:0] $end
$var wire 1 9 readEnable $end
$var wire 32 G writeData [31:0] $end
$var wire 1 H writeEnable $end
$var reg 32 I readData [31:0] $end
$upscope $end
$upscope $end
$upscope $end
$enddefinitions $end
#0
$dumpvars
0!
1"
b0 #
0$
0%
b0 &
b0 '
bx (
b0 )
b0 *
b0 +
0,
1-
b0 .
0/
00
b0 1
b0 2
13
14
05
06
07
08
09
bx :
b0 ;
bx <
b0 =
1>
1?
0@
0A
b0 B
0C
b0 D
b0 E
b0 F
b0 G
0H
bx I
$end
#5000
1!
1,
b0 <
b0 I
#10000
0!
0,
#15000
1!
1,
#20000
0!
0,
#25000
1!
0"
1,
0-
#30000
0!
0,
#35000
1!
1,
#40000
0!
0,
#45000
1!
1,
#50000
0!
b110010 #
1%
b11011110101011011011111011101111 &
0,
b110010 .
10
b11011110101011011011111011101111 1
14
17
bx :
b110010 =
1>
1?
0@
0A
b1100 D
#55000
1!
b11011110101011011011111011101111 (
1,
b11011110101011011011111011101111 :
#56000
0%
00
07
#60000
0!
0,
#65000
1!
1,
#70000
0!
0,
#75000
1!
1,
#80000
0!
b110010 #
1$
0,
1/
#85000
1!
1,
#86000
0$
0/
#90000
0!
0,
#95000
1!
1,
#100000
0!
0,
#105000
1!
1,
#107000
b1 *
#110000
0!
b100000000 #
1%
b1010101111001101 &
b0 (
0,
b100000000 .
10
b1010101111001101 1
03
04
15
07
18
bx :
b100000000 =
0>
0?
1@
0A
b1000000 D
#115000
1!
b1010101111001101 )
1,
b1010101111001101 ;
b1010101111001101 E
#116000
0%
00
08
#120000
0!
0,
#125000
1!
1,
#130000
0!
0,
#135000
1!
1,
#137000
b10 *
#140000
0!
b1000000000 #
1$
b1111000011110000 '
0,
b1000000000 .
1/
b1111000011110000 2
05
16
19
bx :
b1000000000 =
0>
0?
0@
1A
b10000000 D
#145000
1!
b1111000011110000 (
1,
b1111000011110000 <
b1111000011110000 I
#146000
0$
0/
09
#150000
0!
0,
#155000
1!
1,
#160000
0!
0,
#165000
1!
1,
#167000
b11 *
#170000
0!
b100000000 #
1%
b1111111111111111 &
b0 (
0,
b100000000 .
10
b1111111111111111 1
15
06
18
bx :
b100000000 =
0>
0?
1@
0A
b1000000 D
#175000
1!
b1111111111111111 )
1,
b1111111111111111 ;
b1111111111111111 E
#176000
0%
00
08
#180000
0!
0,
#185000
1!
1,
#190000
0!
0,
#195000
1!
1,
#200000
0!
b110010 #
1$
b11011110101011011011111011101111 (
0,
b110010 .
1/
13
14
05
b11011110101011011011111011101111 :
b110010 =
1>
1?
0@
0A
b1100 D
#205000
1!
1,
#206000
0$
0/
#210000
0!
0,
#215000
1!
1,
#220000
0!
0,
#225000
1!
1,
#227000
b100 *
#230000
0!
b110010 #
1%
b11001010111111101011101010111110 &
0,
10
b11001010111111101011101010111110 1
17
#235000
1!
b11001010111111101011101010111110 (
1,
b11001010111111101011101010111110 :
#236000
0%
00
07
#240000
0!
0,
#245000
1!
1,
#250000
0!
0,
#255000
1!
1,
#257000
b1 +
#260000
0!
1"
b0 )
0,
1-
b0 ;
b0 E
#265000
1!
1,
b0 <
b0 I
#270000
0!
0,
#275000
1!
1,
#280000
0!
0,
#285000
1!
0"
1,
0-
b1111000011110000 <
b1111000011110000 I
#290000
0!
0,
#295000
1!
1,
#300000
0!
0,
#305000
1!
1,
#307000
b101 *
