Lab 07/project_3/project_3.srcs/sources_1/new/ALU.v
`timescale 1ns / 1ps
//////////////////////////////////////////////////////////////////////////////////
// Company: 
// Engineer: 
// 
// Create Date: 02/26/2026 09:43:45 AM
// Design Name: 
// Module Name: ALU_module
// Project Name: 
// Target Devices: 
// Tool Versions: 
// Description: 
// 
// Dependencies: 
// 
// Revision:
// Revision 0.01 - File Created
// Additional Comments:
// 
//////////////////////////////////////////////////////////////////////////////////


module ALU(
    input [31:0]A, input [31:0]B,
    input [3:0] ALUControl,
    output reg [31:0]ALUResult,
    output zero
    );
    
    always @(*) begin
        if (ALUControl == 4'b0000) ALUResult <= A+B;
        else if (ALUControl == 4'b0001) ALUResult <= A-B;
        else if (ALUControl == 4'b0010) ALUResult <= A&B;
        else if (ALUControl == 4'b0011) ALUResult <= A|B;
        else if (ALUControl == 4'b0100) ALUResult <= A^B;
        else if (ALUControl == 4'b0101) ALUResult <= A<<B[4:0];
        else if (ALUControl == 4'b0110) ALUResult <= A>>B[4:0];
        else ALUResult <= 32'b0;
        
    end
    
    assign zero = (ALUResult==0);
        
endmodule

Lab 07/project_3/project_3.srcs/sources_1/new/RegisterFile.v
`timescale 1ns / 1ps
//////////////////////////////////////////////////////////////////////////////////
// Company: 
// Engineer: 
// 
// Create Date: 03/05/2026 09:08:32 AM
// Design Name: 
// Module Name: RegisterFile
// Project Name: 
// Target Devices: 
// Tool Versions: 
// Description: 
// 
// Dependencies: 
// 
// Revision:
// Revision 0.01 - File Created
// Additional Comments:
// 
//////////////////////////////////////////////////////////////////////////////////


module RegisterFile(
    input clk, rst, WriteEnable, 
    input [4:0] rs1, rs2, rd,
    input [31:0] WriteData,
    output [31:0] readData1, readData2 
    );
    
    reg[31:0] regs [31:0];
    initial begin
        regs[0] = 32'h00000000; 
        regs[1] = 32'h10101010;
        regs[2] = 32'h01010101;  
    end
    
    always @ (posedge clk) begin
        if (WriteEnable == 1 && rd != 5'b0) regs[rd] <= WriteData; 
    end 
    
    assign readData1=regs[rs1];
    assign readData2=regs[rs2];    
    
    
        
endmodule

Lab 07/project_3/project_3.srcs/sim_1/new/RF_ALU_FSM_tb.v
`timescale 1ns / 1ps

module RF_ALU_FSM_tb;

    // Clock and reset
    reg clk;
    reg reset;
    
    // RegisterFile signals
    reg [4:0] rf_readAddr1;
    reg [4:0] rf_readAddr2;
    wire [31:0] rf_readData1;
    wire [31:0] rf_readData2;
    reg [4:0] rf_writeAddr;
    reg [31:0] rf_writeData;
    reg rf_writeEnable;
    
    // ALU signals
    reg [31:0] alu_A;
    reg [31:0] alu_B;
    reg [3:0] alu_op;
    wire [31:0] alu_result;
    wire alu_zero;
    
    // FSM states
    parameter IDLE           = 5'd0;
    parameter INIT_X1        = 5'd1;
    parameter INIT_X2        = 5'd2;
    parameter INIT_X3        = 5'd3;
    parameter TEST_ADD       = 5'd4;
    parameter TEST_SUB       = 5'd5;
    parameter TEST_AND       = 5'd6;
    parameter TEST_OR        = 5'd7;
    parameter TEST_XOR       = 5'd8;
    parameter TEST_SLL       = 5'd9;
    parameter TEST_SRL       = 5'd10;
    parameter TEST_BEQ       = 5'd11;
    parameter READ_AFTER_WRITE = 5'd12;
    parameter DONE           = 5'd13;
    
    // ALU operation codes
    parameter ADD = 4'b0000;
    parameter SUB = 4'b0001;
    parameter AND = 4'b0010;
    parameter OR  = 4'b0011;
    parameter XOR = 4'b0100;
    parameter SLL = 4'b0101;
    parameter SRL = 4'b0110;
    
    reg [4:0] state;
    reg [4:0] next_state;
    
    // Instantiate RegisterFile
    RegisterFile rf (
        .clk(clk),
        .rst(reset),
        .rs1(rf_readAddr1),
        .readData1(rf_readData1),
        .rs2(rf_readAddr2),
        .readData2(rf_readData2),
        .rd(rf_writeAddr),
        .WriteData(rf_writeData),
        .WriteEnable(rf_writeEnable)
    );
    
    // Instantiate ALU
    ALU alu (
        .A(alu_A),
        .B(alu_B),
        .ALUControl(alu_op),
        .ALUResult(alu_result),
        .zero(alu_zero)
    );
    
    // Clock generation
    initial begin
        clk = 0;
        forever #5 clk = ~clk;
    end
    
    // FSM state register (sequential)
    always @(posedge clk) begin
        if (reset) begin
            state <= IDLE;
        end else begin
            state <= next_state;
        end
    end
    
    // FSM control logic (combinational)
    always @(*) begin
        // Default values
        rf_readAddr1 = 5'b0;
        rf_readAddr2 = 5'b0;
        rf_writeAddr = 5'b0;
        rf_writeData = 32'h0;
        rf_writeEnable = 1'b0;
        alu_A = 32'h0;
        alu_B = 32'h0;
        alu_op = 4'h0;
        
        case (state)
            
            IDLE: begin
                next_state = INIT_X1;
            end
            
            // Initialize registers with known values
            INIT_X1: begin
                rf_writeAddr = 5'd1;
                rf_writeData = 32'h10101010;
                rf_writeEnable = 1'b1;
                next_state = INIT_X2;
            end
            
            INIT_X2: begin
                rf_writeAddr = 5'd2;
                rf_writeData = 32'h01010101;
                rf_writeEnable = 1'b1;
                next_state = INIT_X3;
            end
            
            INIT_X3: begin
                rf_writeAddr = 5'd3;
                rf_writeData = 32'h00000005;
                rf_writeEnable = 1'b1;
                next_state = TEST_ADD;
            end
            
            // Test ALU operations
            TEST_ADD: begin
                rf_readAddr1 = 5'd1;
                rf_readAddr2 = 5'd2;
                alu_A = rf_readData1;
                alu_B = rf_readData2;
                alu_op = ADD;
                rf_writeAddr = 5'd4;
                rf_writeData = alu_result;
                rf_writeEnable = 1'b1;
                next_state = TEST_SUB;
            end
            
            TEST_SUB: begin
                rf_readAddr1 = 5'd1;
                rf_readAddr2 = 5'd2;
                alu_A = rf_readData1;
                alu_B = rf_readData2;
                alu_op = SUB;
                rf_writeAddr = 5'd5;
                rf_writeData = alu_result;
                rf_writeEnable = 1'b1;
                next_state = TEST_AND;
            end
            
            TEST_AND: begin
                rf_readAddr1 = 5'd1;
                rf_readAddr2 = 5'd2;
                alu_A = rf_readData1;
                alu_B = rf_readData2;
                alu_op = AND;
                rf_writeAddr = 5'd6;
                rf_writeData = alu_result;
                rf_writeEnable = 1'b1;
                next_state = TEST_OR;
            end
            
            TEST_OR: begin
                rf_readAddr1 = 5'd1;
                rf_readAddr2 = 5'd2;
                alu_A = rf_readData1;
                alu_B = rf_readData2;
                alu_op = OR;
                rf_writeAddr = 5'd7;
                rf_writeData = alu_result;
                rf_writeEnable = 1'b1;
                next_state = TEST_XOR;
            end
            
            TEST_XOR: begin
                rf_readAddr1 = 5'd1;
                rf_readAddr2 = 5'd2;
                alu_A = rf_readData1;
                alu_B = rf_readData2;
                alu_op = XOR;
                rf_writeAddr = 5'd8;
                rf_writeData = alu_result;
                rf_writeEnable = 1'b1;
                next_state = TEST_SLL;
            end
            
            TEST_SLL: begin
                rf_readAddr1 = 5'd1;
                rf_readAddr2 = 5'd3;
                alu_A = rf_readData1;
                alu_B = rf_readData2;
                alu_op = SLL;
                rf_writeAddr = 5'd9;
                rf_writeData = alu_result;
                rf_writeEnable = 1'b1;
                next_state = TEST_SRL;
            end
            
            TEST_SRL: begin
                rf_readAddr1 = 5'd1;
                rf_readAddr2 = 5'd3;
                alu_A = rf_readData1;
                alu_B = rf_readData2;
                alu_op = SRL;
                rf_writeAddr = 5'd10;
                rf_writeData = alu_result;
                rf_writeEnable = 1'b1;
                next_state = TEST_BEQ;
            end
            
            // Conditional write based on ALU Zero flag
            TEST_BEQ: begin
                rf_readAddr1 = 5'd1;
                rf_readAddr2 = 5'd1;
                alu_A = rf_readData1;
                alu_B = rf_readData2;
                alu_op = SUB;
                
                if (alu_zero) begin
                    rf_writeAddr = 5'd11;
                    rf_writeData = 32'h00000001;
                end else begin
                    rf_writeAddr = 5'd11;
                    rf_writeData = 32'h00000000;
                end
                rf_writeEnable = 1'b1;
                next_state = READ_AFTER_WRITE;
            end
            
            // Read-after-write test
            READ_AFTER_WRITE: begin
                rf_writeAddr = 5'd12;
                rf_writeData = 32'hCAFEBABE;
                rf_writeEnable = 1'b1;
                next_state = DONE;
            end
            
            DONE: begin
                next_state = DONE;
            end
            
            default: begin
                next_state = IDLE;
            end
        endcase
    end
    
    // Test sequence
    initial begin
        reset = 1;
        #10 reset = 0;
        #10;
        
        // Run FSM through all states
        #300;
        
        $finish;
    end
    
    // Generate waveforms
    initial begin
        $dumpfile("RF_ALU_FSM_tb.vcd");
        $dumpvars(0, RF_ALU_FSM_tb);
    end

endmodule

Lab 07/project_3/project_3.sim/sim_1/behav/xsim/RF_ALU_FSM_tb.vcd
$date
   Thu Mar  5 11:25:08 2026
$end
$version
  2020.1
$end
$timescale
  1ps
$end
$scope module RF_ALU_FSM_tb $end
$var reg 1 ! clk $end
$var reg 1 " reset $end
$var reg 5 # rf_readAddr1 [4:0] $end
$var reg 5 $ rf_readAddr2 [4:0] $end
$var wire 32 % rf_readData1 [31:0] $end
$var wire 32 & rf_readData2 [31:0] $end
$var reg 5 ' rf_writeAddr [4:0] $end
$var reg 32 ( rf_writeData [31:0] $end
$var reg 1 ) rf_writeEnable $end
$var reg 32 * alu_A [31:0] $end
$var reg 32 + alu_B [31:0] $end
$var reg 4 , alu_op [3:0] $end
$var wire 32 - alu_result [31:0] $end
$var wire 1 . alu_zero $end
$var reg 5 / state [4:0] $end
$var reg 5 0 next_state [4:0] $end
$var parameter 5 1 IDLE [4:0] $end
$var parameter 5 2 INIT_X1 [4:0] $end
$var parameter 5 3 INIT_X2 [4:0] $end
$var parameter 5 4 INIT_X3 [4:0] $end
$var parameter 5 5 TEST_ADD [4:0] $end
$var parameter 5 6 TEST_SUB [4:0] $end
$var parameter 5 7 TEST_AND [4:0] $end
$var parameter 5 8 TEST_OR [4:0] $end
$var parameter 5 9 TEST_XOR [4:0] $end
$var parameter 5 : TEST_SLL [4:0] $end
$var parameter 5 ; TEST_SRL [4:0] $end
$var parameter 5 < TEST_BEQ [4:0] $end
$var parameter 5 = READ_AFTER_WRITE [4:0] $end
$var parameter 5 > DONE [4:0] $end
$var parameter 4 ? ADD [3:0] $end
$var parameter 4 @ SUB [3:0] $end
$var parameter 4 A AND [3:0] $end
$var parameter 4 B OR [3:0] $end
$var parameter 4 C XOR [3:0] $end
$var parameter 4 D SLL [3:0] $end
$var parameter 4 E SRL [3:0] $end
$scope module rf $end
$var wire 1 F clk $end
$var wire 1 G rst $end
$var wire 1 H WriteEnable $end
$var wire 5 I rs1 [4:0] $end
$var wire 5 J rs2 [4:0] $end
$var wire 5 K rd [4:0] $end
$var wire 32 L WriteData [31:0] $end
$var wire 32 % readData1 [31:0] $end
$var wire 32 & readData2 [31:0] $end
$upscope $end
$scope module alu $end
$var wire 32 M A [31:0] $end
$var wire 32 N B [31:0] $end
$var wire 4 O ALUControl [3:0] $end
$var reg 32 P ALUResult [31:0] $end
$var wire 1 . zero $end
$upscope $end
$upscope $end
$enddefinitions $end
#0
$dumpvars
0!
1"
bx #
bx $
bx %
bx &
bx '
bx (
x)
bx *
bx +
bx ,
bx -
x.
bx /
bx 0
b0 1
b1 2
b10 3
b11 4
b100 5
b101 6
b110 7
b111 8
b1000 9
b1001 :
b1010 ;
b1011 <
b1100 =
b1101 >
b0 ?
b1 @
b10 A
b11 B
b100 C
b101 D
b110 E
0F
1G
xH
bx I
bx J
bx K
bx L
bx M
bx N
bx O
bx P
$end
#5000
1!
b0 #
b0 $
b0 %
b0 &
b0 '
b0 (
0)
b0 *
b0 +
b0 ,
b0 -
1.
b0 /
b1 0
1F
0H
b0 I
b0 J
b0 K
b0 L
b0 M
b0 N
b0 O
b0 P
#10000
0!
0"
0F
0G
#15000
1!
b0 #
b0 $
b1 '
b10000000100000001000000010000 (
1)
b0 *
b0 +
b0 ,
b1 /
b10 0
1F
1H
b1 K
b10000000100000001000000010000 L
#20000
0!
0F
#25000
1!
b0 #
b0 $
b10 '
b1000000010000000100000001 (
1)
b0 *
b0 +
b0 ,
b10 /
b11 0
1F
b10 K
b1000000010000000100000001 L
#30000
0!
0F
#35000
1!
b0 #
b0 $
b11 '
b101 (
1)
b0 *
b0 +
b0 ,
b11 /
b100 0
1F
b11 K
b101 L
#40000
0!
0F
#45000
1!
b1 #
b10 $
b10000000100000001000000010000 %
b1000000010000000100000001 &
b100 '
b10001000100010001000100010001 (
1)
b10000000100000001000000010000 *
b1000000010000000100000001 +
b0 ,
b10001000100010001000100010001 -
0.
b100 /
b101 0
1F
b1 I
b10 J
b100 K
b10001000100010001000100010001 L
b10000000100000001000000010000 M
b1000000010000000100000001 N
b10001000100010001000100010001 P
#50000
0!
0F
#55000
1!
b1 #
b10 $
b10000000100000001000000010000 %
b1000000010000000100000001 &
b101 '
b1111000011110000111100001111 (
1)
b10000000100000001000000010000 *
b1000000010000000100000001 +
b1 ,
b1111000011110000111100001111 -
0.
b101 /
b110 0
1F
b1 I
b10 J
b101 K
b1111000011110000111100001111 L
b10000000100000001000000010000 M
b1000000010000000100000001 N
b1 O
b1111000011110000111100001111 P
#60000
0!
0F
#65000
1!
b1 #
b10 $
b10000000100000001000000010000 %
b1000000010000000100000001 &
b110 '
b0 (
1)
b10000000100000001000000010000 *
b1000000010000000100000001 +
b10 ,
b0 -
1.
b110 /
b111 0
1F
b1 I
b10 J
b110 K
b0 L
b10000000100000001000000010000 M
b1000000010000000100000001 N
b10 O
b0 P
#70000
0!
0F
#75000
1!
b1 #
b10 $
b10000000100000001000000010000 %
b1000000010000000100000001 &
b111 '
b10001000100010001000100010001 (
1)
b10000000100000001000000010000 *
b1000000010000000100000001 +
b11 ,
b10001000100010001000100010001 -
0.
b111 /
b1000 0
1F
b1 I
b10 J
b111 K
b10001000100010001000100010001 L
b10000000100000001000000010000 M
b1000000010000000100000001 N
b11 O
b10001000100010001000100010001 P
#80000
0!
0F
#85000
1!
b1 #
b10 $
b10000000100000001000000010000 %
b1000000010000000100000001 &
b1000 '
b10001000100010001000100010001 (
1)
b10000000100000001000000010000 *
b1000000010000000100000001 +
b100 ,
b1000 /
b1001 0
1F
b1 I
b10 J
b1000 K
b10000000100000001000000010000 M
b1000000010000000100000001 N
b100 O
#90000
0!
0F
#95000
1!
b1 #
b11 $
b10000000100000001000000010000 %
b101 &
b1001 '
b10000000100000001000000000 (
1)
b10000000100000001000000010000 *
b101 +
b101 ,
b10000000100000001000000000 -
0.
b1001 /
b1010 0
1F
b1 I
b11 J
b1001 K
b10000000100000001000000000 L
b10000000100000001000000010000 M
b101 N
b101 O
b10000000100000001000000000 P
#100000
0!
0F
#105000
1!
b1 #
b11 $
b10000000100000001000000010000 %
b101 &
b1010 '
b100000001000000010000000 (
1)
b10000000100000001000000010000 *
b101 +
b110 ,
b100000001000000010000000 -
0.
b1010 /
b1011 0
1F
b1 I
b11 J
b1010 K
b100000001000000010000000 L
b10000000100000001000000010000 M
b101 N
b110 O
b100000001000000010000000 P
#110000
0!
0F
#115000
1!
b1 #
b1 $
b10000000100000001000000010000 %
b10000000100000001000000010000 &
b1011 '
b1 (
1)
b10000000100000001000000010000 *
b10000000100000001000000010000 +
b1 ,
b0 -
1.
b1011 /
b1100 0
1F
b1 I
b1 J
b1011 K
b1 L
b10000000100000001000000010000 M
b10000000100000001000000010000 N
b1 O
b0 P
#120000
0!
0F
#125000
1!
b0 #
b0 $
b0 %
b0 &
b1100 '
b11001010111111101011101010111110 (
1)
b0 *
b0 +
b0 ,
b1100 /
b1101 0
1F
b0 I
b0 J
b1100 K
b11001010111111101011101010111110 L
b0 M
b0 N
b0 O
#130000
0!
0F
#135000
1!
b0 #
b0 $
b0 %
b0 &
b0 '
b0 (
0)
b0 *
b0 +
b0 ,
b1101 /
1F
0H
b0 K
b0 L
